claudetracing/__init__.py
claudetracing/cli.py
claudetracing/client.py
claudetracing/enrichments.py
claudetracing/formatters.py
claudetracing/git_enrichment.py
claudetracing/hooks.py
claudetracing/models.py
claudetracing/setup.py
claudetracing-0.2.0.dist-info/METADATA
claudetracing-0.2.0.dist-info/WHEEL
claudetracing-0.2.0.dist-info/entry_points.txt
claudetracing-0.2.0.dist-info/licenses/LICENSE
claudetracing-0.2.0.dist-info/RECORD
