Metadata-Version: 2.4
Name: claudetracing
Version: 0.2.0
Summary: MLflow tracing for Claude Code sessions with Databricks integration
Project-URL: Homepage, https://github.com/CauchyIO/claudetracing
Project-URL: Repository, https://github.com/CauchyIO/claudetracing
Project-URL: Issues, https://github.com/CauchyIO/claudetracing/issues
Author: Casper
License-Expression: MIT
License-File: LICENSE
Keywords: claude,databricks,llm,mlflow,tracing
Classifier: Development Status :: 4 - Beta
Classifier: Environment :: Console
Classifier: Intended Audience :: Developers
Classifier: License :: OSI Approved :: MIT License
Classifier: Programming Language :: Python :: 3
Classifier: Programming Language :: Python :: 3.10
Classifier: Programming Language :: Python :: 3.11
Classifier: Programming Language :: Python :: 3.12
Classifier: Topic :: Software Development :: Libraries :: Python Modules
Requires-Python: >=3.10
Requires-Dist: mlflow[databricks]>=3.4
Requires-Dist: pydantic>=2.0
Requires-Dist: ty>=0.0.8
Requires-Dist: typer>=0.9
